biosynth_emg/__init__.py
biosynth_emg/biomechanical.py
biosynth_emg/electrical.py
biosynth_emg/generator.py
biosynth_emg/validation.py
biosynth_emg-0.1.0.dist-info/licenses/LICENSE
biosynth_emg-0.1.0.dist-info/METADATA
biosynth_emg-0.1.0.dist-info/WHEEL
biosynth_emg-0.1.0.dist-info/top_level.txt
biosynth_emg-0.1.0.dist-info/RECORD
